{
    "Slave11": {
        "Flows": []
    },
    "Slave0": {
        "Flows": []
    },
    "Slave35": {
        "Flows": []
    },
    "Slave4": {
        "Flows": []
    },
    "Slave24": {
        "Flows": []
    },
    "Slave19": {
        "Flows": []
    },
    "Slave13": {
        "Flows": []
    },
    "Slave23": {
        "Flows": []
    },
    "Slave28": {
        "Flows": []
    },
    "Slave21": {
        "Flows": []
    },
    "Slave15": {
        "Flows": []
    },
    "Master": {
        "Flows": [
            {
                "Bandwidth": 128000,
                "Periodic": false,
                "Header": [
                    "ADDR",
                    "SIZE"
                ],
                "Payload": [
                    "0000FFFF",
                    "40EF7E55"
                ],
                "StopTime": 0,
                "SourceThread": "Master",
                "MSGAmount": 1,
                "StartTime": 0,
                "ControlFlowFlag": false,
                "TargetThread": "Slave0"
            },
            {
                "Bandwidth": 128000,
                "Periodic": false,
                "Header": [
                    "ADDR",
                    "SIZE"
                ],
                "Payload": [
                    "0000FFFF",
                    "40CAFB05"
                ],
                "StopTime": 0,
                "SourceThread": "Master",
                "MSGAmount": 1,
                "StartTime": 0,
                "ControlFlowFlag": false,
                "TargetThread": "Slave1"
            },
            {
                "Bandwidth": 128000,
                "Periodic": false,
                "Header": [
                    "ADDR",
                    "SIZE"
                ],
                "Payload": [
                    "0000FFFF",
                    "4004007D"
                ],
                "StopTime": 0,
                "SourceThread": "Master",
                "MSGAmount": 1,
                "StartTime": 0,
                "ControlFlowFlag": false,
                "TargetThread": "Slave2"
            },
            {
                "Bandwidth": 128000,
                "Periodic": false,
                "Header": [
                    "ADDR",
                    "SIZE"
                ],
                "Payload": [
                    "0000FFFF",
                    "4004007D"
                ],
                "StopTime": 0,
                "SourceThread": "Master",
                "MSGAmount": 1,
                "StartTime": 0,
                "ControlFlowFlag": false,
                "TargetThread": "Slave3"
            },
            {
                "Bandwidth": 128000,
                "Periodic": false,
                "Header": [
                    "ADDR",
                    "SIZE"
                ],
                "Payload": [
                    "0000FFFF",
                    "4008007D"
                ],
                "StopTime": 0,
                "SourceThread": "Master",
                "MSGAmount": 1,
                "StartTime": 0,
                "ControlFlowFlag": false,
                "TargetThread": "Slave4"
            },
            {
                "Bandwidth": 128000,
                "Periodic": false,
                "Header": [
                    "ADDR",
                    "SIZE"
                ],
                "Payload": [
                    "0000FFFF",
                    "400C007D"
                ],
                "StopTime": 0,
                "SourceThread": "Master",
                "MSGAmount": 1,
                "StartTime": 0,
                "ControlFlowFlag": false,
                "TargetThread": "Slave5"
            },
            {
                "Bandwidth": 128000,
                "Periodic": false,
                "Header": [
                    "ADDR",
                    "SIZE"
                ],
                "Payload": [
                    "0000FFFF",
                    "4161E1A8"
                ],
                "StopTime": 0,
                "SourceThread": "Master",
                "MSGAmount": 1,
                "StartTime": 0,
                "ControlFlowFlag": false,
                "TargetThread": "Slave6"
            },
            {
                "Bandwidth": 128000,
                "Periodic": false,
                "Header": [
                    "ADDR",
                    "SIZE"
                ],
                "Payload": [
                    "0000FFFF",
                    "4047ECAD"
                ],
                "StopTime": 0,
                "SourceThread": "Master",
                "MSGAmount": 1,
                "StartTime": 0,
                "ControlFlowFlag": false,
                "TargetThread": "Slave7"
            },
            {
                "Bandwidth": 128000,
                "Periodic": false,
                "Header": [
                    "ADDR",
                    "SIZE"
                ],
                "Payload": [
                    "0000FFFF",
                    "4004007D"
                ],
                "StopTime": 0,
                "SourceThread": "Master",
                "MSGAmount": 1,
                "StartTime": 0,
                "ControlFlowFlag": false,
                "TargetThread": "Slave8"
            },
            {
                "Bandwidth": 128000,
                "Periodic": false,
                "Header": [
                    "ADDR",
                    "SIZE"
                ],
                "Payload": [
                    "0000FFFF",
                    "4008007D"
                ],
                "StopTime": 0,
                "SourceThread": "Master",
                "MSGAmount": 1,
                "StartTime": 0,
                "ControlFlowFlag": false,
                "TargetThread": "Slave9"
            },
            {
                "Bandwidth": 128000,
                "Periodic": false,
                "Header": [
                    "ADDR",
                    "SIZE"
                ],
                "Payload": [
                    "0000FFFF",
                    "4004007D"
                ],
                "StopTime": 0,
                "SourceThread": "Master",
                "MSGAmount": 1,
                "StartTime": 0,
                "ControlFlowFlag": false,
                "TargetThread": "Slave10"
            },
            {
                "Bandwidth": 128000,
                "Periodic": false,
                "Header": [
                    "ADDR",
                    "SIZE"
                ],
                "Payload": [
                    "0000FFFF",
                    "4004007D"
                ],
                "StopTime": 0,
                "SourceThread": "Master",
                "MSGAmount": 1,
                "StartTime": 0,
                "ControlFlowFlag": false,
                "TargetThread": "Slave11"
            },
            {
                "Bandwidth": 128000,
                "Periodic": false,
                "Header": [
                    "ADDR",
                    "SIZE"
                ],
                "Payload": [
                    "0000FFFF",
                    "400480C8"
                ],
                "StopTime": 0,
                "SourceThread": "Master",
                "MSGAmount": 1,
                "StartTime": 0,
                "ControlFlowFlag": false,
                "TargetThread": "Slave12"
            },
            {
                "Bandwidth": 128000,
                "Periodic": false,
                "Header": [
                    "ADDR",
                    "SIZE"
                ],
                "Payload": [
                    "0000FFFF",
                    "431A7EF5"
                ],
                "StopTime": 0,
                "SourceThread": "Master",
                "MSGAmount": 1,
                "StartTime": 0,
                "ControlFlowFlag": false,
                "TargetThread": "Slave13"
            },
            {
                "Bandwidth": 128000,
                "Periodic": false,
                "Header": [
                    "ADDR",
                    "SIZE"
                ],
                "Payload": [
                    "0000FFFF",
                    "431A7EF5"
                ],
                "StopTime": 0,
                "SourceThread": "Master",
                "MSGAmount": 1,
                "StartTime": 0,
                "ControlFlowFlag": false,
                "TargetThread": "Slave14"
            },
            {
                "Bandwidth": 128000,
                "Periodic": false,
                "Header": [
                    "ADDR",
                    "SIZE"
                ],
                "Payload": [
                    "0000FFFF",
                    "4006007D"
                ],
                "StopTime": 0,
                "SourceThread": "Master",
                "MSGAmount": 1,
                "StartTime": 0,
                "ControlFlowFlag": false,
                "TargetThread": "Slave15"
            },
            {
                "Bandwidth": 128000,
                "Periodic": false,
                "Header": [
                    "ADDR",
                    "SIZE"
                ],
                "Payload": [
                    "0000FFFF",
                    "40020019"
                ],
                "StopTime": 0,
                "SourceThread": "Master",
                "MSGAmount": 1,
                "StartTime": 0,
                "ControlFlowFlag": false,
                "TargetThread": "Slave16"
            },
            {
                "Bandwidth": 128000,
                "Periodic": false,
                "Header": [
                    "ADDR",
                    "SIZE"
                ],
                "Payload": [
                    "0000FFFF",
                    "4004007D"
                ],
                "StopTime": 0,
                "SourceThread": "Master",
                "MSGAmount": 1,
                "StartTime": 0,
                "ControlFlowFlag": false,
                "TargetThread": "Slave17"
            },
            {
                "Bandwidth": 128000,
                "Periodic": false,
                "Header": [
                    "ADDR",
                    "SIZE"
                ],
                "Payload": [
                    "0000FFFF",
                    "40048064"
                ],
                "StopTime": 0,
                "SourceThread": "Master",
                "MSGAmount": 1,
                "StartTime": 0,
                "ControlFlowFlag": false,
                "TargetThread": "Slave18"
            },
            {
                "Bandwidth": 128000,
                "Periodic": false,
                "Header": [
                    "ADDR",
                    "SIZE"
                ],
                "Payload": [
                    "0000FFFF",
                    "40048032"
                ],
                "StopTime": 0,
                "SourceThread": "Master",
                "MSGAmount": 1,
                "StartTime": 0,
                "ControlFlowFlag": false,
                "TargetThread": "Slave19"
            },
            {
                "Bandwidth": 128000,
                "Periodic": false,
                "Header": [
                    "ADDR",
                    "SIZE"
                ],
                "Payload": [
                    "0000FFFF",
                    "426FB333"
                ],
                "StopTime": 0,
                "SourceThread": "Master",
                "MSGAmount": 1,
                "StartTime": 0,
                "ControlFlowFlag": false,
                "TargetThread": "Slave20"
            },
            {
                "Bandwidth": 128000,
                "Periodic": false,
                "Header": [
                    "ADDR",
                    "SIZE"
                ],
                "Payload": [
                    "0000FFFF",
                    "4006007D"
                ],
                "StopTime": 0,
                "SourceThread": "Master",
                "MSGAmount": 1,
                "StartTime": 0,
                "ControlFlowFlag": false,
                "TargetThread": "Slave21"
            },
            {
                "Bandwidth": 128000,
                "Periodic": false,
                "Header": [
                    "ADDR",
                    "SIZE"
                ],
                "Payload": [
                    "0000FFFF",
                    "400C007D"
                ],
                "StopTime": 0,
                "SourceThread": "Master",
                "MSGAmount": 1,
                "StartTime": 0,
                "ControlFlowFlag": false,
                "TargetThread": "Slave22"
            },
            {
                "Bandwidth": 128000,
                "Periodic": false,
                "Header": [
                    "ADDR",
                    "SIZE"
                ],
                "Payload": [
                    "0000FFFF",
                    "4008007D"
                ],
                "StopTime": 0,
                "SourceThread": "Master",
                "MSGAmount": 1,
                "StartTime": 0,
                "ControlFlowFlag": false,
                "TargetThread": "Slave23"
            },
            {
                "Bandwidth": 128000,
                "Periodic": false,
                "Header": [
                    "ADDR",
                    "SIZE"
                ],
                "Payload": [
                    "0000FFFF",
                    "40018019"
                ],
                "StopTime": 0,
                "SourceThread": "Master",
                "MSGAmount": 1,
                "StartTime": 0,
                "ControlFlowFlag": false,
                "TargetThread": "Slave24"
            },
            {
                "Bandwidth": 128000,
                "Periodic": false,
                "Header": [
                    "ADDR",
                    "SIZE"
                ],
                "Payload": [
                    "0000FFFF",
                    "4001800A"
                ],
                "StopTime": 0,
                "SourceThread": "Master",
                "MSGAmount": 1,
                "StartTime": 0,
                "ControlFlowFlag": false,
                "TargetThread": "Slave25"
            },
            {
                "Bandwidth": 128000,
                "Periodic": false,
                "Header": [
                    "ADDR",
                    "SIZE"
                ],
                "Payload": [
                    "0000FFFF",
                    "40018019"
                ],
                "StopTime": 0,
                "SourceThread": "Master",
                "MSGAmount": 1,
                "StartTime": 0,
                "ControlFlowFlag": false,
                "TargetThread": "Slave26"
            },
            {
                "Bandwidth": 128000,
                "Periodic": false,
                "Header": [
                    "ADDR",
                    "SIZE"
                ],
                "Payload": [
                    "0000FFFF",
                    "4006007D"
                ],
                "StopTime": 0,
                "SourceThread": "Master",
                "MSGAmount": 1,
                "StartTime": 0,
                "ControlFlowFlag": false,
                "TargetThread": "Slave27"
            },
            {
                "Bandwidth": 128000,
                "Periodic": false,
                "Header": [
                    "ADDR",
                    "SIZE"
                ],
                "Payload": [
                    "0000FFFF",
                    "400C007D"
                ],
                "StopTime": 0,
                "SourceThread": "Master",
                "MSGAmount": 1,
                "StartTime": 0,
                "ControlFlowFlag": false,
                "TargetThread": "Slave28"
            },
            {
                "Bandwidth": 128000,
                "Periodic": false,
                "Header": [
                    "ADDR",
                    "SIZE"
                ],
                "Payload": [
                    "0000FFFF",
                    "4006007D"
                ],
                "StopTime": 0,
                "SourceThread": "Master",
                "MSGAmount": 1,
                "StartTime": 0,
                "ControlFlowFlag": false,
                "TargetThread": "Slave29"
            },
            {
                "Bandwidth": 128000,
                "Periodic": false,
                "Header": [
                    "ADDR",
                    "SIZE"
                ],
                "Payload": [
                    "0000FFFF",
                    "4404CE20"
                ],
                "StopTime": 0,
                "SourceThread": "Master",
                "MSGAmount": 1,
                "StartTime": 0,
                "ControlFlowFlag": false,
                "TargetThread": "Slave30"
            },
            {
                "Bandwidth": 128000,
                "Periodic": false,
                "Header": [
                    "ADDR",
                    "SIZE"
                ],
                "Payload": [
                    "0000FFFF",
                    "40048032"
                ],
                "StopTime": 0,
                "SourceThread": "Master",
                "MSGAmount": 1,
                "StartTime": 0,
                "ControlFlowFlag": false,
                "TargetThread": "Slave31"
            },
            {
                "Bandwidth": 128000,
                "Periodic": false,
                "Header": [
                    "ADDR",
                    "SIZE"
                ],
                "Payload": [
                    "0000FFFF",
                    "40000001"
                ],
                "StopTime": 0,
                "SourceThread": "Master",
                "MSGAmount": 1,
                "StartTime": 0,
                "ControlFlowFlag": false,
                "TargetThread": "Slave32"
            },
            {
                "Bandwidth": 128000,
                "Periodic": false,
                "Header": [
                    "ADDR",
                    "SIZE"
                ],
                "Payload": [
                    "0000FFFF",
                    "4004007D"
                ],
                "StopTime": 0,
                "SourceThread": "Master",
                "MSGAmount": 1,
                "StartTime": 0,
                "ControlFlowFlag": false,
                "TargetThread": "Slave33"
            },
            {
                "Bandwidth": 128000,
                "Periodic": false,
                "Header": [
                    "ADDR",
                    "SIZE"
                ],
                "Payload": [
                    "0000FFFF",
                    "4006007D"
                ],
                "StopTime": 0,
                "SourceThread": "Master",
                "MSGAmount": 1,
                "StartTime": 0,
                "ControlFlowFlag": false,
                "TargetThread": "Slave34"
            },
            {
                "Bandwidth": 128000,
                "Periodic": false,
                "Header": [
                    "ADDR",
                    "SIZE"
                ],
                "Payload": [
                    "0000FFFF",
                    "4006007D"
                ],
                "StopTime": 0,
                "SourceThread": "Master",
                "MSGAmount": 1,
                "StartTime": 0,
                "ControlFlowFlag": false,
                "TargetThread": "Slave35"
            },
            {
                "Bandwidth": 128000,
                "Periodic": false,
                "Header": [
                    "ADDR",
                    "SIZE"
                ],
                "Payload": [
                    "0000FFFF",
                    "4171E1A8"
                ],
                "StopTime": 0,
                "SourceThread": "Master",
                "MSGAmount": 1,
                "StartTime": 1000000,
                "ControlFlowFlag": false,
                "TargetThread": "Slave0"
            },
            {
                "Bandwidth": 128000,
                "Periodic": false,
                "Header": [
                    "ADDR",
                    "SIZE"
                ],
                "Payload": [
                    "0000FFFF",
                    "4141E1A8"
                ],
                "StopTime": 0,
                "SourceThread": "Master",
                "MSGAmount": 1,
                "StartTime": 1000000,
                "ControlFlowFlag": false,
                "TargetThread": "Slave1"
            },
            {
                "Bandwidth": 128000,
                "Periodic": false,
                "Header": [
                    "ADDR",
                    "SIZE"
                ],
                "Payload": [
                    "0000FFFF",
                    "40000001"
                ],
                "StopTime": 0,
                "SourceThread": "Master",
                "MSGAmount": 1,
                "StartTime": 1000000,
                "ControlFlowFlag": false,
                "TargetThread": "Slave2"
            },
            {
                "Bandwidth": 128000,
                "Periodic": false,
                "Header": [
                    "ADDR",
                    "SIZE"
                ],
                "Payload": [
                    "0000FFFF",
                    "40000001"
                ],
                "StopTime": 0,
                "SourceThread": "Master",
                "MSGAmount": 1,
                "StartTime": 1000000,
                "ControlFlowFlag": false,
                "TargetThread": "Slave3"
            },
            {
                "Bandwidth": 128000,
                "Periodic": false,
                "Header": [
                    "ADDR",
                    "SIZE"
                ],
                "Payload": [
                    "0000FFFF",
                    "4141E1A8"
                ],
                "StopTime": 0,
                "SourceThread": "Master",
                "MSGAmount": 1,
                "StartTime": 1000000,
                "ControlFlowFlag": false,
                "TargetThread": "Slave4"
            },
            {
                "Bandwidth": 128000,
                "Periodic": false,
                "Header": [
                    "ADDR",
                    "SIZE"
                ],
                "Payload": [
                    "0000FFFF",
                    "4171E1A8"
                ],
                "StopTime": 0,
                "SourceThread": "Master",
                "MSGAmount": 1,
                "StartTime": 1000000,
                "ControlFlowFlag": false,
                "TargetThread": "Slave5"
            },
            {
                "Bandwidth": 128000,
                "Periodic": false,
                "Header": [
                    "ADDR",
                    "SIZE"
                ],
                "Payload": [
                    "0000FFFF",
                    "4161B0D4"
                ],
                "StopTime": 0,
                "SourceThread": "Master",
                "MSGAmount": 1,
                "StartTime": 1000000,
                "ControlFlowFlag": false,
                "TargetThread": "Slave6"
            },
            {
                "Bandwidth": 128000,
                "Periodic": false,
                "Header": [
                    "ADDR",
                    "SIZE"
                ],
                "Payload": [
                    "0000FFFF",
                    "4047ECAD"
                ],
                "StopTime": 0,
                "SourceThread": "Master",
                "MSGAmount": 1,
                "StartTime": 1000000,
                "ControlFlowFlag": false,
                "TargetThread": "Slave7"
            },
            {
                "Bandwidth": 128000,
                "Periodic": false,
                "Header": [
                    "ADDR",
                    "SIZE"
                ],
                "Payload": [
                    "0000FFFF",
                    "4047ECAD"
                ],
                "StopTime": 0,
                "SourceThread": "Master",
                "MSGAmount": 1,
                "StartTime": 1000000,
                "ControlFlowFlag": false,
                "TargetThread": "Slave8"
            },
            {
                "Bandwidth": 128000,
                "Periodic": false,
                "Header": [
                    "ADDR",
                    "SIZE"
                ],
                "Payload": [
                    "0000FFFF",
                    "4047ECAD"
                ],
                "StopTime": 0,
                "SourceThread": "Master",
                "MSGAmount": 1,
                "StartTime": 1000000,
                "ControlFlowFlag": false,
                "TargetThread": "Slave9"
            },
            {
                "Bandwidth": 128000,
                "Periodic": false,
                "Header": [
                    "ADDR",
                    "SIZE"
                ],
                "Payload": [
                    "0000FFFF",
                    "4047ECAD"
                ],
                "StopTime": 0,
                "SourceThread": "Master",
                "MSGAmount": 1,
                "StartTime": 1000000,
                "ControlFlowFlag": false,
                "TargetThread": "Slave10"
            },
            {
                "Bandwidth": 128000,
                "Periodic": false,
                "Header": [
                    "ADDR",
                    "SIZE"
                ],
                "Payload": [
                    "0000FFFF",
                    "4161B0D4"
                ],
                "StopTime": 0,
                "SourceThread": "Master",
                "MSGAmount": 1,
                "StartTime": 1000000,
                "ControlFlowFlag": false,
                "TargetThread": "Slave11"
            },
            {
                "Bandwidth": 128000,
                "Periodic": false,
                "Header": [
                    "ADDR",
                    "SIZE"
                ],
                "Payload": [
                    "0000FFFF",
                    "40048064"
                ],
                "StopTime": 0,
                "SourceThread": "Master",
                "MSGAmount": 1,
                "StartTime": 1000000,
                "ControlFlowFlag": false,
                "TargetThread": "Slave12"
            },
            {
                "Bandwidth": 128000,
                "Periodic": false,
                "Header": [
                    "ADDR",
                    "SIZE"
                ],
                "Payload": [
                    "0000FFFF",
                    "43D7CEA3"
                ],
                "StopTime": 0,
                "SourceThread": "Master",
                "MSGAmount": 1,
                "StartTime": 1000000,
                "ControlFlowFlag": false,
                "TargetThread": "Slave13"
            },
            {
                "Bandwidth": 128000,
                "Periodic": false,
                "Header": [
                    "ADDR",
                    "SIZE"
                ],
                "Payload": [
                    "0000FFFF",
                    "43D7CEA3"
                ],
                "StopTime": 0,
                "SourceThread": "Master",
                "MSGAmount": 1,
                "StartTime": 1000000,
                "ControlFlowFlag": false,
                "TargetThread": "Slave14"
            },
            {
                "Bandwidth": 128000,
                "Periodic": false,
                "Header": [
                    "ADDR",
                    "SIZE"
                ],
                "Payload": [
                    "0000FFFF",
                    "43D7CEA3"
                ],
                "StopTime": 0,
                "SourceThread": "Master",
                "MSGAmount": 1,
                "StartTime": 1000000,
                "ControlFlowFlag": false,
                "TargetThread": "Slave15"
            },
            {
                "Bandwidth": 128000,
                "Periodic": false,
                "Header": [
                    "ADDR",
                    "SIZE"
                ],
                "Payload": [
                    "0000FFFF",
                    "43D7CEA3"
                ],
                "StopTime": 0,
                "SourceThread": "Master",
                "MSGAmount": 1,
                "StartTime": 1000000,
                "ControlFlowFlag": false,
                "TargetThread": "Slave16"
            },
            {
                "Bandwidth": 128000,
                "Periodic": false,
                "Header": [
                    "ADDR",
                    "SIZE"
                ],
                "Payload": [
                    "0000FFFF",
                    "40048064"
                ],
                "StopTime": 0,
                "SourceThread": "Master",
                "MSGAmount": 1,
                "StartTime": 1000000,
                "ControlFlowFlag": false,
                "TargetThread": "Slave17"
            },
            {
                "Bandwidth": 128000,
                "Periodic": false,
                "Header": [
                    "ADDR",
                    "SIZE"
                ],
                "Payload": [
                    "0000FFFF",
                    "40048032"
                ],
                "StopTime": 0,
                "SourceThread": "Master",
                "MSGAmount": 1,
                "StartTime": 1000000,
                "ControlFlowFlag": false,
                "TargetThread": "Slave18"
            },
            {
                "Bandwidth": 128000,
                "Periodic": false,
                "Header": [
                    "ADDR",
                    "SIZE"
                ],
                "Payload": [
                    "0000FFFF",
                    "40048019"
                ],
                "StopTime": 0,
                "SourceThread": "Master",
                "MSGAmount": 1,
                "StartTime": 1000000,
                "ControlFlowFlag": false,
                "TargetThread": "Slave19"
            },
            {
                "Bandwidth": 128000,
                "Periodic": false,
                "Header": [
                    "ADDR",
                    "SIZE"
                ],
                "Payload": [
                    "0000FFFF",
                    "494AE1A8"
                ],
                "StopTime": 0,
                "SourceThread": "Master",
                "MSGAmount": 1,
                "StartTime": 1000000,
                "ControlFlowFlag": false,
                "TargetThread": "Slave20"
            },
            {
                "Bandwidth": 128000,
                "Periodic": false,
                "Header": [
                    "ADDR",
                    "SIZE"
                ],
                "Payload": [
                    "0000FFFF",
                    "494AE1A8"
                ],
                "StopTime": 0,
                "SourceThread": "Master",
                "MSGAmount": 1,
                "StartTime": 1000000,
                "ControlFlowFlag": false,
                "TargetThread": "Slave21"
            },
            {
                "Bandwidth": 128000,
                "Periodic": false,
                "Header": [
                    "ADDR",
                    "SIZE"
                ],
                "Payload": [
                    "0000FFFF",
                    "40048019"
                ],
                "StopTime": 0,
                "SourceThread": "Master",
                "MSGAmount": 1,
                "StartTime": 1000000,
                "ControlFlowFlag": false,
                "TargetThread": "Slave22"
            },
            {
                "Bandwidth": 128000,
                "Periodic": false,
                "Header": [
                    "ADDR",
                    "SIZE"
                ],
                "Payload": [
                    "0000FFFF",
                    "40048032"
                ],
                "StopTime": 0,
                "SourceThread": "Master",
                "MSGAmount": 1,
                "StartTime": 1000000,
                "ControlFlowFlag": false,
                "TargetThread": "Slave23"
            },
            {
                "Bandwidth": 128000,
                "Periodic": false,
                "Header": [
                    "ADDR",
                    "SIZE"
                ],
                "Payload": [
                    "0000FFFF",
                    "40030019"
                ],
                "StopTime": 0,
                "SourceThread": "Master",
                "MSGAmount": 1,
                "StartTime": 1000000,
                "ControlFlowFlag": false,
                "TargetThread": "Slave24"
            },
            {
                "Bandwidth": 128000,
                "Periodic": false,
                "Header": [
                    "ADDR",
                    "SIZE"
                ],
                "Payload": [
                    "0000FFFF",
                    "C0018005"
                ],
                "StopTime": 0,
                "SourceThread": "Master",
                "MSGAmount": 1,
                "StartTime": 1000000,
                "ControlFlowFlag": false,
                "TargetThread": "Slave25"
            },
            {
                "Bandwidth": 128000,
                "Periodic": false,
                "Header": [
                    "ADDR",
                    "SIZE"
                ],
                "Payload": [
                    "0000FFFF",
                    "40030019"
                ],
                "StopTime": 0,
                "SourceThread": "Master",
                "MSGAmount": 1,
                "StartTime": 1000000,
                "ControlFlowFlag": false,
                "TargetThread": "Slave26"
            },
            {
                "Bandwidth": 128000,
                "Periodic": false,
                "Header": [
                    "ADDR",
                    "SIZE"
                ],
                "Payload": [
                    "0000FFFF",
                    "40030019"
                ],
                "StopTime": 0,
                "SourceThread": "Master",
                "MSGAmount": 1,
                "StartTime": 1000000,
                "ControlFlowFlag": false,
                "TargetThread": "Slave27"
            },
            {
                "Bandwidth": 128000,
                "Periodic": false,
                "Header": [
                    "ADDR",
                    "SIZE"
                ],
                "Payload": [
                    "0000FFFF",
                    "C0018005"
                ],
                "StopTime": 0,
                "SourceThread": "Master",
                "MSGAmount": 1,
                "StartTime": 1000000,
                "ControlFlowFlag": false,
                "TargetThread": "Slave28"
            },
            {
                "Bandwidth": 128000,
                "Periodic": false,
                "Header": [
                    "ADDR",
                    "SIZE"
                ],
                "Payload": [
                    "0000FFFF",
                    "40030019"
                ],
                "StopTime": 0,
                "SourceThread": "Master",
                "MSGAmount": 1,
                "StartTime": 1000000,
                "ControlFlowFlag": false,
                "TargetThread": "Slave29"
            },
            {
                "Bandwidth": 128000,
                "Periodic": false,
                "Header": [
                    "ADDR",
                    "SIZE"
                ],
                "Payload": [
                    "0000FFFF",
                    "40018019"
                ],
                "StopTime": 0,
                "SourceThread": "Master",
                "MSGAmount": 1,
                "StartTime": 1000000,
                "ControlFlowFlag": false,
                "TargetThread": "Slave30"
            },
            {
                "Bandwidth": 128000,
                "Periodic": false,
                "Header": [
                    "ADDR",
                    "SIZE"
                ],
                "Payload": [
                    "0000FFFF",
                    "40048019"
                ],
                "StopTime": 0,
                "SourceThread": "Master",
                "MSGAmount": 1,
                "StartTime": 1000000,
                "ControlFlowFlag": false,
                "TargetThread": "Slave31"
            },
            {
                "Bandwidth": 128000,
                "Periodic": false,
                "Header": [
                    "ADDR",
                    "SIZE"
                ],
                "Payload": [
                    "0000FFFF",
                    "40000001"
                ],
                "StopTime": 0,
                "SourceThread": "Master",
                "MSGAmount": 1,
                "StartTime": 1000000,
                "ControlFlowFlag": false,
                "TargetThread": "Slave32"
            },
            {
                "Bandwidth": 128000,
                "Periodic": false,
                "Header": [
                    "ADDR",
                    "SIZE"
                ],
                "Payload": [
                    "0000FFFF",
                    "40000001"
                ],
                "StopTime": 0,
                "SourceThread": "Master",
                "MSGAmount": 1,
                "StartTime": 1000000,
                "ControlFlowFlag": false,
                "TargetThread": "Slave33"
            },
            {
                "Bandwidth": 128000,
                "Periodic": false,
                "Header": [
                    "ADDR",
                    "SIZE"
                ],
                "Payload": [
                    "0000FFFF",
                    "40048019"
                ],
                "StopTime": 0,
                "SourceThread": "Master",
                "MSGAmount": 1,
                "StartTime": 1000000,
                "ControlFlowFlag": false,
                "TargetThread": "Slave34"
            },
            {
                "Bandwidth": 128000,
                "Periodic": false,
                "Header": [
                    "ADDR",
                    "SIZE"
                ],
                "Payload": [
                    "0000FFFF",
                    "40018019"
                ],
                "StopTime": 0,
                "SourceThread": "Master",
                "MSGAmount": 1,
                "StartTime": 1000000,
                "ControlFlowFlag": false,
                "TargetThread": "Slave35"
            },
            {
                "Bandwidth": 128000,
                "Periodic": false,
                "Header": [
                    "ADDR",
                    "SIZE"
                ],
                "Payload": [
                    "0000FFFF",
                    "4002CE00"
                ],
                "StopTime": 0,
                "SourceThread": "Master",
                "MSGAmount": 1,
                "StartTime": 2000000,
                "ControlFlowFlag": false,
                "TargetThread": "Slave0"
            },
            {
                "Bandwidth": 128000,
                "Periodic": false,
                "Header": [
                    "ADDR",
                    "SIZE"
                ],
                "Payload": [
                    "0000FFFF",
                    "406A87D0"
                ],
                "StopTime": 0,
                "SourceThread": "Master",
                "MSGAmount": 1,
                "StartTime": 2000000,
                "ControlFlowFlag": false,
                "TargetThread": "Slave1"
            },
            {
                "Bandwidth": 128000,
                "Periodic": false,
                "Header": [
                    "ADDR",
                    "SIZE"
                ],
                "Payload": [
                    "0000FFFF",
                    "40008004"
                ],
                "StopTime": 0,
                "SourceThread": "Master",
                "MSGAmount": 1,
                "StartTime": 2000000,
                "ControlFlowFlag": false,
                "TargetThread": "Slave2"
            },
            {
                "Bandwidth": 128000,
                "Periodic": false,
                "Header": [
                    "ADDR",
                    "SIZE"
                ],
                "Payload": [
                    "0000FFFF",
                    "40008FA0"
                ],
                "StopTime": 0,
                "SourceThread": "Master",
                "MSGAmount": 1,
                "StartTime": 2000000,
                "ControlFlowFlag": false,
                "TargetThread": "Slave3"
            },
            {
                "Bandwidth": 128000,
                "Periodic": false,
                "Header": [
                    "ADDR",
                    "SIZE"
                ],
                "Payload": [
                    "0000FFFF",
                    "406A87D0"
                ],
                "StopTime": 0,
                "SourceThread": "Master",
                "MSGAmount": 1,
                "StartTime": 2000000,
                "ControlFlowFlag": false,
                "TargetThread": "Slave4"
            },
            {
                "Bandwidth": 128000,
                "Periodic": false,
                "Header": [
                    "ADDR",
                    "SIZE"
                ],
                "Payload": [
                    "0000FFFF",
                    "40008004"
                ],
                "StopTime": 0,
                "SourceThread": "Master",
                "MSGAmount": 1,
                "StartTime": 2000000,
                "ControlFlowFlag": false,
                "TargetThread": "Slave5"
            },
            {
                "Bandwidth": 128000,
                "Periodic": false,
                "Header": [
                    "ADDR",
                    "SIZE"
                ],
                "Payload": [
                    "0000FFFF",
                    "40008FA0"
                ],
                "StopTime": 0,
                "SourceThread": "Master",
                "MSGAmount": 1,
                "StartTime": 2000000,
                "ControlFlowFlag": false,
                "TargetThread": "Slave6"
            },
            {
                "Bandwidth": 128000,
                "Periodic": false,
                "Header": [
                    "ADDR",
                    "SIZE"
                ],
                "Payload": [
                    "0000FFFF",
                    "40008002"
                ],
                "StopTime": 0,
                "SourceThread": "Master",
                "MSGAmount": 1,
                "StartTime": 2000000,
                "ControlFlowFlag": false,
                "TargetThread": "Slave7"
            },
            {
                "Bandwidth": 128000,
                "Periodic": false,
                "Header": [
                    "ADDR",
                    "SIZE"
                ],
                "Payload": [
                    "0000FFFF",
                    "C39987D0"
                ],
                "StopTime": 0,
                "SourceThread": "Master",
                "MSGAmount": 1,
                "StartTime": 2000000,
                "ControlFlowFlag": false,
                "TargetThread": "Slave8"
            },
            {
                "Bandwidth": 128000,
                "Periodic": false,
                "Header": [
                    "ADDR",
                    "SIZE"
                ],
                "Payload": [
                    "0000FFFF",
                    "40008FA0"
                ],
                "StopTime": 0,
                "SourceThread": "Master",
                "MSGAmount": 1,
                "StartTime": 2000000,
                "ControlFlowFlag": false,
                "TargetThread": "Slave9"
            },
            {
                "Bandwidth": 128000,
                "Periodic": false,
                "Header": [
                    "ADDR",
                    "SIZE"
                ],
                "Payload": [
                    "0000FFFF",
                    "40008002"
                ],
                "StopTime": 0,
                "SourceThread": "Master",
                "MSGAmount": 1,
                "StartTime": 2000000,
                "ControlFlowFlag": false,
                "TargetThread": "Slave10"
            },
            {
                "Bandwidth": 128000,
                "Periodic": false,
                "Header": [
                    "ADDR",
                    "SIZE"
                ],
                "Payload": [
                    "0000FFFF",
                    "C39987D0"
                ],
                "StopTime": 0,
                "SourceThread": "Master",
                "MSGAmount": 1,
                "StartTime": 2000000,
                "ControlFlowFlag": false,
                "TargetThread": "Slave11"
            },
            {
                "Bandwidth": 128000,
                "Periodic": false,
                "Header": [
                    "ADDR",
                    "SIZE"
                ],
                "Payload": [
                    "0000FFFF",
                    "400980C8"
                ],
                "StopTime": 0,
                "SourceThread": "Master",
                "MSGAmount": 1,
                "StartTime": 2000000,
                "ControlFlowFlag": false,
                "TargetThread": "Slave12"
            },
            {
                "Bandwidth": 128000,
                "Periodic": false,
                "Header": [
                    "ADDR",
                    "SIZE"
                ],
                "Payload": [
                    "0000FFFF",
                    "C1668320"
                ],
                "StopTime": 0,
                "SourceThread": "Master",
                "MSGAmount": 1,
                "StartTime": 2000000,
                "ControlFlowFlag": false,
                "TargetThread": "Slave13"
            },
            {
                "Bandwidth": 128000,
                "Periodic": false,
                "Header": [
                    "ADDR",
                    "SIZE"
                ],
                "Payload": [
                    "0000FFFF",
                    "C0278064"
                ],
                "StopTime": 0,
                "SourceThread": "Master",
                "MSGAmount": 1,
                "StartTime": 2000000,
                "ControlFlowFlag": false,
                "TargetThread": "Slave14"
            },
            {
                "Bandwidth": 128000,
                "Periodic": false,
                "Header": [
                    "ADDR",
                    "SIZE"
                ],
                "Payload": [
                    "0000FFFF",
                    "400980C8"
                ],
                "StopTime": 0,
                "SourceThread": "Master",
                "MSGAmount": 1,
                "StartTime": 2000000,
                "ControlFlowFlag": false,
                "TargetThread": "Slave15"
            },
            {
                "Bandwidth": 128000,
                "Periodic": false,
                "Header": [
                    "ADDR",
                    "SIZE"
                ],
                "Payload": [
                    "0000FFFF",
                    "C1668320"
                ],
                "StopTime": 0,
                "SourceThread": "Master",
                "MSGAmount": 1,
                "StartTime": 2000000,
                "ControlFlowFlag": false,
                "TargetThread": "Slave16"
            },
            {
                "Bandwidth": 128000,
                "Periodic": false,
                "Header": [
                    "ADDR",
                    "SIZE"
                ],
                "Payload": [
                    "0000FFFF",
                    "C0278064"
                ],
                "StopTime": 0,
                "SourceThread": "Master",
                "MSGAmount": 1,
                "StartTime": 2000000,
                "ControlFlowFlag": false,
                "TargetThread": "Slave17"
            },
            {
                "Bandwidth": 128000,
                "Periodic": false,
                "Header": [
                    "ADDR",
                    "SIZE"
                ],
                "Payload": [
                    "0000FFFF",
                    "40008019"
                ],
                "StopTime": 0,
                "SourceThread": "Master",
                "MSGAmount": 1,
                "StartTime": 2000000,
                "ControlFlowFlag": false,
                "TargetThread": "Slave18"
            },
            {
                "Bandwidth": 128000,
                "Periodic": false,
                "Header": [
                    "ADDR",
                    "SIZE"
                ],
                "Payload": [
                    "0000FFFF",
                    "40040019"
                ],
                "StopTime": 0,
                "SourceThread": "Master",
                "MSGAmount": 1,
                "StartTime": 2000000,
                "ControlFlowFlag": false,
                "TargetThread": "Slave19"
            },
            {
                "Bandwidth": 128000,
                "Periodic": false,
                "Header": [
                    "ADDR",
                    "SIZE"
                ],
                "Payload": [
                    "0000FFFF",
                    "40008014"
                ],
                "StopTime": 0,
                "SourceThread": "Master",
                "MSGAmount": 1,
                "StartTime": 2000000,
                "ControlFlowFlag": false,
                "TargetThread": "Slave20"
            },
            {
                "Bandwidth": 128000,
                "Periodic": false,
                "Header": [
                    "ADDR",
                    "SIZE"
                ],
                "Payload": [
                    "0000FFFF",
                    "40008019"
                ],
                "StopTime": 0,
                "SourceThread": "Master",
                "MSGAmount": 1,
                "StartTime": 2000000,
                "ControlFlowFlag": false,
                "TargetThread": "Slave21"
            },
            {
                "Bandwidth": 128000,
                "Periodic": false,
                "Header": [
                    "ADDR",
                    "SIZE"
                ],
                "Payload": [
                    "0000FFFF",
                    "40040019"
                ],
                "StopTime": 0,
                "SourceThread": "Master",
                "MSGAmount": 1,
                "StartTime": 2000000,
                "ControlFlowFlag": false,
                "TargetThread": "Slave22"
            },
            {
                "Bandwidth": 128000,
                "Periodic": false,
                "Header": [
                    "ADDR",
                    "SIZE"
                ],
                "Payload": [
                    "0000FFFF",
                    "40008014"
                ],
                "StopTime": 0,
                "SourceThread": "Master",
                "MSGAmount": 1,
                "StartTime": 2000000,
                "ControlFlowFlag": false,
                "TargetThread": "Slave23"
            },
            {
                "Bandwidth": 128000,
                "Periodic": false,
                "Header": [
                    "ADDR",
                    "SIZE"
                ],
                "Payload": [
                    "0000FFFF",
                    "4002007D"
                ],
                "StopTime": 0,
                "SourceThread": "Master",
                "MSGAmount": 1,
                "StartTime": 2000000,
                "ControlFlowFlag": false,
                "TargetThread": "Slave24"
            },
            {
                "Bandwidth": 128000,
                "Periodic": false,
                "Header": [
                    "ADDR",
                    "SIZE"
                ],
                "Payload": [
                    "0000FFFF",
                    "C0020005"
                ],
                "StopTime": 0,
                "SourceThread": "Master",
                "MSGAmount": 1,
                "StartTime": 2000000,
                "ControlFlowFlag": false,
                "TargetThread": "Slave25"
            },
            {
                "Bandwidth": 128000,
                "Periodic": false,
                "Header": [
                    "ADDR",
                    "SIZE"
                ],
                "Payload": [
                    "0000FFFF",
                    "C09481F4"
                ],
                "StopTime": 0,
                "SourceThread": "Master",
                "MSGAmount": 1,
                "StartTime": 2000000,
                "ControlFlowFlag": false,
                "TargetThread": "Slave26"
            },
            {
                "Bandwidth": 128000,
                "Periodic": false,
                "Header": [
                    "ADDR",
                    "SIZE"
                ],
                "Payload": [
                    "0000FFFF",
                    "401883E8"
                ],
                "StopTime": 0,
                "SourceThread": "Master",
                "MSGAmount": 1,
                "StartTime": 2000000,
                "ControlFlowFlag": false,
                "TargetThread": "Slave27"
            },
            {
                "Bandwidth": 128000,
                "Periodic": false,
                "Header": [
                    "ADDR",
                    "SIZE"
                ],
                "Payload": [
                    "0000FFFF",
                    "405A81F4"
                ],
                "StopTime": 0,
                "SourceThread": "Master",
                "MSGAmount": 1,
                "StartTime": 2000000,
                "ControlFlowFlag": false,
                "TargetThread": "Slave28"
            },
            {
                "Bandwidth": 128000,
                "Periodic": false,
                "Header": [
                    "ADDR",
                    "SIZE"
                ],
                "Payload": [
                    "0000FFFF",
                    "405A81F4"
                ],
                "StopTime": 0,
                "SourceThread": "Master",
                "MSGAmount": 1,
                "StartTime": 2000000,
                "ControlFlowFlag": false,
                "TargetThread": "Slave29"
            },
            {
                "Bandwidth": 128000,
                "Periodic": false,
                "Header": [
                    "ADDR",
                    "SIZE"
                ],
                "Payload": [
                    "0000FFFF",
                    "40D383E8"
                ],
                "StopTime": 0,
                "SourceThread": "Master",
                "MSGAmount": 1,
                "StartTime": 2000000,
                "ControlFlowFlag": false,
                "TargetThread": "Slave30"
            },
            {
                "Bandwidth": 128000,
                "Periodic": false,
                "Header": [
                    "ADDR",
                    "SIZE"
                ],
                "Payload": [
                    "0000FFFF",
                    "40B083E8"
                ],
                "StopTime": 0,
                "SourceThread": "Master",
                "MSGAmount": 1,
                "StartTime": 2000000,
                "ControlFlowFlag": false,
                "TargetThread": "Slave31"
            },
            {
                "Bandwidth": 128000,
                "Periodic": false,
                "Header": [
                    "ADDR",
                    "SIZE"
                ],
                "Payload": [
                    "0000FFFF",
                    "40BA83E8"
                ],
                "StopTime": 0,
                "SourceThread": "Master",
                "MSGAmount": 1,
                "StartTime": 2000000,
                "ControlFlowFlag": false,
                "TargetThread": "Slave32"
            },
            {
                "Bandwidth": 128000,
                "Periodic": false,
                "Header": [
                    "ADDR",
                    "SIZE"
                ],
                "Payload": [
                    "0000FFFF",
                    "40C283E8"
                ],
                "StopTime": 0,
                "SourceThread": "Master",
                "MSGAmount": 1,
                "StartTime": 2000000,
                "ControlFlowFlag": false,
                "TargetThread": "Slave33"
            },
            {
                "Bandwidth": 128000,
                "Periodic": false,
                "Header": [
                    "ADDR",
                    "SIZE"
                ],
                "Payload": [
                    "0000FFFF",
                    "40CD83E8"
                ],
                "StopTime": 0,
                "SourceThread": "Master",
                "MSGAmount": 1,
                "StartTime": 2000000,
                "ControlFlowFlag": false,
                "TargetThread": "Slave34"
            },
            {
                "Bandwidth": 128000,
                "Periodic": false,
                "Header": [
                    "ADDR",
                    "SIZE"
                ],
                "Payload": [
                    "0000FFFF",
                    "40038064"
                ],
                "StopTime": 0,
                "SourceThread": "Master",
                "MSGAmount": 1,
                "StartTime": 2000000,
                "ControlFlowFlag": false,
                "TargetThread": "Slave35"
            },
            {
                "Bandwidth": 128000,
                "Periodic": false,
                "Header": [
                    "ADDR",
                    "SIZE"
                ],
                "Payload": [
                    "0000FFFF",
                    "4171E1A8"
                ],
                "StopTime": 0,
                "SourceThread": "Master",
                "MSGAmount": 1,
                "StartTime": 3000000,
                "ControlFlowFlag": false,
                "TargetThread": "Slave0"
            },
            {
                "Bandwidth": 128000,
                "Periodic": false,
                "Header": [
                    "ADDR",
                    "SIZE"
                ],
                "Payload": [
                    "0000FFFF",
                    "4141E1A8"
                ],
                "StopTime": 0,
                "SourceThread": "Master",
                "MSGAmount": 1,
                "StartTime": 3000000,
                "ControlFlowFlag": false,
                "TargetThread": "Slave1"
            },
            {
                "Bandwidth": 128000,
                "Periodic": false,
                "Header": [
                    "ADDR",
                    "SIZE"
                ],
                "Payload": [
                    "0000FFFF",
                    "4004007D"
                ],
                "StopTime": 0,
                "SourceThread": "Master",
                "MSGAmount": 1,
                "StartTime": 3000000,
                "ControlFlowFlag": false,
                "TargetThread": "Slave2"
            },
            {
                "Bandwidth": 128000,
                "Periodic": false,
                "Header": [
                    "ADDR",
                    "SIZE"
                ],
                "Payload": [
                    "0000FFFF",
                    "4004007D"
                ],
                "StopTime": 0,
                "SourceThread": "Master",
                "MSGAmount": 1,
                "StartTime": 3000000,
                "ControlFlowFlag": false,
                "TargetThread": "Slave3"
            },
            {
                "Bandwidth": 128000,
                "Periodic": false,
                "Header": [
                    "ADDR",
                    "SIZE"
                ],
                "Payload": [
                    "0000FFFF",
                    "4008007D"
                ],
                "StopTime": 0,
                "SourceThread": "Master",
                "MSGAmount": 1,
                "StartTime": 3000000,
                "ControlFlowFlag": false,
                "TargetThread": "Slave4"
            },
            {
                "Bandwidth": 128000,
                "Periodic": false,
                "Header": [
                    "ADDR",
                    "SIZE"
                ],
                "Payload": [
                    "0000FFFF",
                    "400C007D"
                ],
                "StopTime": 0,
                "SourceThread": "Master",
                "MSGAmount": 1,
                "StartTime": 3000000,
                "ControlFlowFlag": false,
                "TargetThread": "Slave5"
            },
            {
                "Bandwidth": 128000,
                "Periodic": false,
                "Header": [
                    "ADDR",
                    "SIZE"
                ],
                "Payload": [
                    "0000FFFF",
                    "4161B0D4"
                ],
                "StopTime": 0,
                "SourceThread": "Master",
                "MSGAmount": 1,
                "StartTime": 3000000,
                "ControlFlowFlag": false,
                "TargetThread": "Slave6"
            },
            {
                "Bandwidth": 128000,
                "Periodic": false,
                "Header": [
                    "ADDR",
                    "SIZE"
                ],
                "Payload": [
                    "0000FFFF",
                    "4047ECAD"
                ],
                "StopTime": 0,
                "SourceThread": "Master",
                "MSGAmount": 1,
                "StartTime": 3000000,
                "ControlFlowFlag": false,
                "TargetThread": "Slave7"
            },
            {
                "Bandwidth": 128000,
                "Periodic": false,
                "Header": [
                    "ADDR",
                    "SIZE"
                ],
                "Payload": [
                    "0000FFFF",
                    "4004007D"
                ],
                "StopTime": 0,
                "SourceThread": "Master",
                "MSGAmount": 1,
                "StartTime": 3000000,
                "ControlFlowFlag": false,
                "TargetThread": "Slave8"
            },
            {
                "Bandwidth": 128000,
                "Periodic": false,
                "Header": [
                    "ADDR",
                    "SIZE"
                ],
                "Payload": [
                    "0000FFFF",
                    "4008007D"
                ],
                "StopTime": 0,
                "SourceThread": "Master",
                "MSGAmount": 1,
                "StartTime": 3000000,
                "ControlFlowFlag": false,
                "TargetThread": "Slave9"
            },
            {
                "Bandwidth": 128000,
                "Periodic": false,
                "Header": [
                    "ADDR",
                    "SIZE"
                ],
                "Payload": [
                    "0000FFFF",
                    "4004007D"
                ],
                "StopTime": 0,
                "SourceThread": "Master",
                "MSGAmount": 1,
                "StartTime": 3000000,
                "ControlFlowFlag": false,
                "TargetThread": "Slave10"
            },
            {
                "Bandwidth": 128000,
                "Periodic": false,
                "Header": [
                    "ADDR",
                    "SIZE"
                ],
                "Payload": [
                    "0000FFFF",
                    "4004007D"
                ],
                "StopTime": 0,
                "SourceThread": "Master",
                "MSGAmount": 1,
                "StartTime": 3000000,
                "ControlFlowFlag": false,
                "TargetThread": "Slave11"
            },
            {
                "Bandwidth": 128000,
                "Periodic": false,
                "Header": [
                    "ADDR",
                    "SIZE"
                ],
                "Payload": [
                    "0000FFFF",
                    "40048064"
                ],
                "StopTime": 0,
                "SourceThread": "Master",
                "MSGAmount": 1,
                "StartTime": 3000000,
                "ControlFlowFlag": false,
                "TargetThread": "Slave12"
            },
            {
                "Bandwidth": 128000,
                "Periodic": false,
                "Header": [
                    "ADDR",
                    "SIZE"
                ],
                "Payload": [
                    "0000FFFF",
                    "43203D73"
                ],
                "StopTime": 0,
                "SourceThread": "Master",
                "MSGAmount": 1,
                "StartTime": 3000000,
                "ControlFlowFlag": false,
                "TargetThread": "Slave13"
            },
            {
                "Bandwidth": 128000,
                "Periodic": false,
                "Header": [
                    "ADDR",
                    "SIZE"
                ],
                "Payload": [
                    "0000FFFF",
                    "43D7CEA3"
                ],
                "StopTime": 0,
                "SourceThread": "Master",
                "MSGAmount": 1,
                "StartTime": 3000000,
                "ControlFlowFlag": false,
                "TargetThread": "Slave14"
            },
            {
                "Bandwidth": 128000,
                "Periodic": false,
                "Header": [
                    "ADDR",
                    "SIZE"
                ],
                "Payload": [
                    "0000FFFF",
                    "4006007D"
                ],
                "StopTime": 0,
                "SourceThread": "Master",
                "MSGAmount": 1,
                "StartTime": 3000000,
                "ControlFlowFlag": false,
                "TargetThread": "Slave15"
            },
            {
                "Bandwidth": 128000,
                "Periodic": false,
                "Header": [
                    "ADDR",
                    "SIZE"
                ],
                "Payload": [
                    "0000FFFF",
                    "40020019"
                ],
                "StopTime": 0,
                "SourceThread": "Master",
                "MSGAmount": 1,
                "StartTime": 3000000,
                "ControlFlowFlag": false,
                "TargetThread": "Slave16"
            },
            {
                "Bandwidth": 128000,
                "Periodic": false,
                "Header": [
                    "ADDR",
                    "SIZE"
                ],
                "Payload": [
                    "0000FFFF",
                    "40018032"
                ],
                "StopTime": 0,
                "SourceThread": "Master",
                "MSGAmount": 1,
                "StartTime": 3000000,
                "ControlFlowFlag": false,
                "TargetThread": "Slave17"
            },
            {
                "Bandwidth": 128000,
                "Periodic": false,
                "Header": [
                    "ADDR",
                    "SIZE"
                ],
                "Payload": [
                    "0000FFFF",
                    "40048032"
                ],
                "StopTime": 0,
                "SourceThread": "Master",
                "MSGAmount": 1,
                "StartTime": 3000000,
                "ControlFlowFlag": false,
                "TargetThread": "Slave18"
            },
            {
                "Bandwidth": 128000,
                "Periodic": false,
                "Header": [
                    "ADDR",
                    "SIZE"
                ],
                "Payload": [
                    "0000FFFF",
                    "40048019"
                ],
                "StopTime": 0,
                "SourceThread": "Master",
                "MSGAmount": 1,
                "StartTime": 3000000,
                "ControlFlowFlag": false,
                "TargetThread": "Slave19"
            },
            {
                "Bandwidth": 128000,
                "Periodic": false,
                "Header": [
                    "ADDR",
                    "SIZE"
                ],
                "Payload": [
                    "0000FFFF",
                    "494AE1A8"
                ],
                "StopTime": 0,
                "SourceThread": "Master",
                "MSGAmount": 1,
                "StartTime": 3000000,
                "ControlFlowFlag": false,
                "TargetThread": "Slave20"
            },
            {
                "Bandwidth": 128000,
                "Periodic": false,
                "Header": [
                    "ADDR",
                    "SIZE"
                ],
                "Payload": [
                    "0000FFFF",
                    "4006007D"
                ],
                "StopTime": 0,
                "SourceThread": "Master",
                "MSGAmount": 1,
                "StartTime": 3000000,
                "ControlFlowFlag": false,
                "TargetThread": "Slave21"
            },
            {
                "Bandwidth": 128000,
                "Periodic": false,
                "Header": [
                    "ADDR",
                    "SIZE"
                ],
                "Payload": [
                    "0000FFFF",
                    "400C007D"
                ],
                "StopTime": 0,
                "SourceThread": "Master",
                "MSGAmount": 1,
                "StartTime": 3000000,
                "ControlFlowFlag": false,
                "TargetThread": "Slave22"
            },
            {
                "Bandwidth": 128000,
                "Periodic": false,
                "Header": [
                    "ADDR",
                    "SIZE"
                ],
                "Payload": [
                    "0000FFFF",
                    "4008007D"
                ],
                "StopTime": 0,
                "SourceThread": "Master",
                "MSGAmount": 1,
                "StartTime": 3000000,
                "ControlFlowFlag": false,
                "TargetThread": "Slave23"
            },
            {
                "Bandwidth": 128000,
                "Periodic": false,
                "Header": [
                    "ADDR",
                    "SIZE"
                ],
                "Payload": [
                    "0000FFFF",
                    "40030019"
                ],
                "StopTime": 0,
                "SourceThread": "Master",
                "MSGAmount": 1,
                "StartTime": 3000000,
                "ControlFlowFlag": false,
                "TargetThread": "Slave24"
            },
            {
                "Bandwidth": 128000,
                "Periodic": false,
                "Header": [
                    "ADDR",
                    "SIZE"
                ],
                "Payload": [
                    "0000FFFF",
                    "C0018005"
                ],
                "StopTime": 0,
                "SourceThread": "Master",
                "MSGAmount": 1,
                "StartTime": 3000000,
                "ControlFlowFlag": false,
                "TargetThread": "Slave25"
            },
            {
                "Bandwidth": 128000,
                "Periodic": false,
                "Header": [
                    "ADDR",
                    "SIZE"
                ],
                "Payload": [
                    "0000FFFF",
                    "40030019"
                ],
                "StopTime": 0,
                "SourceThread": "Master",
                "MSGAmount": 1,
                "StartTime": 3000000,
                "ControlFlowFlag": false,
                "TargetThread": "Slave26"
            },
            {
                "Bandwidth": 128000,
                "Periodic": false,
                "Header": [
                    "ADDR",
                    "SIZE"
                ],
                "Payload": [
                    "0000FFFF",
                    "4006007D"
                ],
                "StopTime": 0,
                "SourceThread": "Master",
                "MSGAmount": 1,
                "StartTime": 3000000,
                "ControlFlowFlag": false,
                "TargetThread": "Slave27"
            },
            {
                "Bandwidth": 128000,
                "Periodic": false,
                "Header": [
                    "ADDR",
                    "SIZE"
                ],
                "Payload": [
                    "0000FFFF",
                    "400C007D"
                ],
                "StopTime": 0,
                "SourceThread": "Master",
                "MSGAmount": 1,
                "StartTime": 3000000,
                "ControlFlowFlag": false,
                "TargetThread": "Slave28"
            },
            {
                "Bandwidth": 128000,
                "Periodic": false,
                "Header": [
                    "ADDR",
                    "SIZE"
                ],
                "Payload": [
                    "0000FFFF",
                    "4006007D"
                ],
                "StopTime": 0,
                "SourceThread": "Master",
                "MSGAmount": 1,
                "StartTime": 3000000,
                "ControlFlowFlag": false,
                "TargetThread": "Slave29"
            },
            {
                "Bandwidth": 128000,
                "Periodic": false,
                "Header": [
                    "ADDR",
                    "SIZE"
                ],
                "Payload": [
                    "0000FFFF",
                    "40020019"
                ],
                "StopTime": 0,
                "SourceThread": "Master",
                "MSGAmount": 1,
                "StartTime": 3000000,
                "ControlFlowFlag": false,
                "TargetThread": "Slave30"
            },
            {
                "Bandwidth": 128000,
                "Periodic": false,
                "Header": [
                    "ADDR",
                    "SIZE"
                ],
                "Payload": [
                    "0000FFFF",
                    "40048019"
                ],
                "StopTime": 0,
                "SourceThread": "Master",
                "MSGAmount": 1,
                "StartTime": 3000000,
                "ControlFlowFlag": false,
                "TargetThread": "Slave31"
            },
            {
                "Bandwidth": 128000,
                "Periodic": false,
                "Header": [
                    "ADDR",
                    "SIZE"
                ],
                "Payload": [
                    "0000FFFF",
                    "40000001"
                ],
                "StopTime": 0,
                "SourceThread": "Master",
                "MSGAmount": 1,
                "StartTime": 3000000,
                "ControlFlowFlag": false,
                "TargetThread": "Slave32"
            },
            {
                "Bandwidth": 128000,
                "Periodic": false,
                "Header": [
                    "ADDR",
                    "SIZE"
                ],
                "Payload": [
                    "0000FFFF",
                    "4004007D"
                ],
                "StopTime": 0,
                "SourceThread": "Master",
                "MSGAmount": 1,
                "StartTime": 3000000,
                "ControlFlowFlag": false,
                "TargetThread": "Slave33"
            },
            {
                "Bandwidth": 128000,
                "Periodic": false,
                "Header": [
                    "ADDR",
                    "SIZE"
                ],
                "Payload": [
                    "0000FFFF",
                    "4006007D"
                ],
                "StopTime": 0,
                "SourceThread": "Master",
                "MSGAmount": 1,
                "StartTime": 3000000,
                "ControlFlowFlag": false,
                "TargetThread": "Slave34"
            },
            {
                "Bandwidth": 128000,
                "Periodic": false,
                "Header": [
                    "ADDR",
                    "SIZE"
                ],
                "Payload": [
                    "0000FFFF",
                    "4006007D"
                ],
                "StopTime": 0,
                "SourceThread": "Master",
                "MSGAmount": 1,
                "StartTime": 3000000,
                "ControlFlowFlag": false,
                "TargetThread": "Slave35"
            }
        ]
    },
    "Slave10": {
        "Flows": []
    },
    "Slave2": {
        "Flows": []
    },
    "Slave29": {
        "Flows": []
    },
    "Slave8": {
        "Flows": []
    },
    "Slave14": {
        "Flows": []
    },
    "Slave20": {
        "Flows": []
    },
    "Slave26": {
        "Flows": []
    },
    "Slave32": {
        "Flows": []
    },
    "Slave31": {
        "Flows": []
    },
    "Slave7": {
        "Flows": []
    },
    "Slave16": {
        "Flows": []
    },
    "Slave25": {
        "Flows": []
    },
    "Slave18": {
        "Flows": []
    },
    "Slave22": {
        "Flows": []
    },
    "Slave3": {
        "Flows": []
    },
    "Slave33": {
        "Flows": []
    },
    "StartTime": 0,
    "Slave9": {
        "Flows": []
    },
    "Slave17": {
        "Flows": []
    },
    "Slave27": {
        "Flows": []
    },
    "Slave6": {
        "Flows": []
    },
    "Slave12": {
        "Flows": []
    },
    "Slave5": {
        "Flows": []
    },
    "Slave1": {
        "Flows": []
    },
    "StopTime": 0,
    "Slave30": {
        "Flows": []
    },
    "Slave34": {
        "Flows": []
    },
    "AppName": "DVFSApp"
}