{
    "AppName": "DVFSApp",
    "AmountOfThreads": 37,
    "StopTime": 0,
    "AppID": null,
    "Threads": [
        {
            "ThreadID": 0,
            "ThreadName": "Sink",
            "AmountOfOutgoingFlows": 0,
            "OutgoingFlows": [],
            "AmountOfIncomingFlows": 76
        },
        {
            "ThreadID": 1,
            "ThreadName": "Source0",
            "AmountOfOutgoingFlows": 0,
            "OutgoingFlows": [],
            "AmountOfIncomingFlows": 0
        },
        {
            "ThreadID": 2,
            "ThreadName": "Source1",
            "AmountOfOutgoingFlows": 4,
            "OutgoingFlows": [
                {
                    "MSGAmount": 1,
                    "SourceThread": "Source1",
                    "FlowType": "CBR",
                    "Header": [
                        "ADDR",
                        "SIZE"
                    ],
                    "StopTime": 0,
                    "Bandwidth": 1000,
                    "Payload": [
                        "0000FFFF",
                        "4008007D"
                    ],
                    "TargetThread": "Sink",
                    "Periodic": false,
                    "StartTime": 0
                },
                {
                    "MSGAmount": 1,
                    "SourceThread": "Source1",
                    "FlowType": "CBR",
                    "Header": [
                        "ADDR",
                        "SIZE"
                    ],
                    "StopTime": 0,
                    "Bandwidth": 1000,
                    "Payload": [
                        "0000FFFF",
                        "4000FFFF"
                    ],
                    "TargetThread": "Sink",
                    "Periodic": false,
                    "StartTime": 1000000
                },
                {
                    "MSGAmount": 1,
                    "SourceThread": "Source1",
                    "FlowType": "CBR",
                    "Header": [
                        "ADDR",
                        "SIZE"
                    ],
                    "StopTime": 0,
                    "Bandwidth": 1000,
                    "Payload": [
                        "0000FFFF",
                        "405A81F4"
                    ],
                    "TargetThread": "Sink",
                    "Periodic": false,
                    "StartTime": 2000000
                },
                {
                    "MSGAmount": 1,
                    "SourceThread": "Source1",
                    "FlowType": "CBR",
                    "Header": [
                        "ADDR",
                        "SIZE"
                    ],
                    "StopTime": 0,
                    "Bandwidth": 1000,
                    "Payload": [
                        "0000FFFF",
                        "4008007D"
                    ],
                    "TargetThread": "Sink",
                    "Periodic": false,
                    "StartTime": 3000000
                }
            ],
            "AmountOfIncomingFlows": 0
        },
        {
            "ThreadID": 3,
            "ThreadName": "Source2",
            "AmountOfOutgoingFlows": 4,
            "OutgoingFlows": [
                {
                    "MSGAmount": 1,
                    "SourceThread": "Source2",
                    "FlowType": "CBR",
                    "Header": [
                        "ADDR",
                        "SIZE"
                    ],
                    "StopTime": 0,
                    "Bandwidth": 1000,
                    "Payload": [
                        "0000FFFF",
                        "4004007D"
                    ],
                    "TargetThread": "Sink",
                    "Periodic": false,
                    "StartTime": 0
                },
                {
                    "MSGAmount": 1,
                    "SourceThread": "Source2",
                    "FlowType": "CBR",
                    "Header": [
                        "ADDR",
                        "SIZE"
                    ],
                    "StopTime": 0,
                    "Bandwidth": 1000,
                    "Payload": [
                        "0000FFFF",
                        "4000FFFF"
                    ],
                    "TargetThread": "Sink",
                    "Periodic": false,
                    "StartTime": 1000000
                },
                {
                    "MSGAmount": 1,
                    "SourceThread": "Source2",
                    "FlowType": "CBR",
                    "Header": [
                        "ADDR",
                        "SIZE"
                    ],
                    "StopTime": 0,
                    "Bandwidth": 1000,
                    "Payload": [
                        "0000FFFF",
                        "40CD83E8"
                    ],
                    "TargetThread": "Sink",
                    "Periodic": false,
                    "StartTime": 2000000
                },
                {
                    "MSGAmount": 1,
                    "SourceThread": "Source2",
                    "FlowType": "CBR",
                    "Header": [
                        "ADDR",
                        "SIZE"
                    ],
                    "StopTime": 0,
                    "Bandwidth": 1000,
                    "Payload": [
                        "0000FFFF",
                        "4004007D"
                    ],
                    "TargetThread": "Sink",
                    "Periodic": false,
                    "StartTime": 3000000
                }
            ],
            "AmountOfIncomingFlows": 0
        },
        {
            "ThreadID": 4,
            "ThreadName": "Source3",
            "AmountOfOutgoingFlows": 4,
            "OutgoingFlows": [
                {
                    "MSGAmount": 1,
                    "SourceThread": "Source3",
                    "FlowType": "CBR",
                    "Header": [
                        "ADDR",
                        "SIZE"
                    ],
                    "StopTime": 0,
                    "Bandwidth": 1000,
                    "Payload": [
                        "0000FFFF",
                        "4000FFFF"
                    ],
                    "TargetThread": "Sink",
                    "Periodic": false,
                    "StartTime": 0
                },
                {
                    "MSGAmount": 1,
                    "SourceThread": "Source3",
                    "FlowType": "CBR",
                    "Header": [
                        "ADDR",
                        "SIZE"
                    ],
                    "StopTime": 0,
                    "Bandwidth": 1000,
                    "Payload": [
                        "0000FFFF",
                        "4000FFFF"
                    ],
                    "TargetThread": "Sink",
                    "Periodic": false,
                    "StartTime": 1000000
                },
                {
                    "MSGAmount": 1,
                    "SourceThread": "Source3",
                    "FlowType": "CBR",
                    "Header": [
                        "ADDR",
                        "SIZE"
                    ],
                    "StopTime": 0,
                    "Bandwidth": 1000,
                    "Payload": [
                        "0000FFFF",
                        "401883E8"
                    ],
                    "TargetThread": "Sink",
                    "Periodic": false,
                    "StartTime": 2000000
                },
                {
                    "MSGAmount": 1,
                    "SourceThread": "Source3",
                    "FlowType": "CBR",
                    "Header": [
                        "ADDR",
                        "SIZE"
                    ],
                    "StopTime": 0,
                    "Bandwidth": 1000,
                    "Payload": [
                        "0000FFFF",
                        "4000FFFF"
                    ],
                    "TargetThread": "Sink",
                    "Periodic": false,
                    "StartTime": 3000000
                }
            ],
            "AmountOfIncomingFlows": 0
        },
        {
            "ThreadID": 5,
            "ThreadName": "Source4",
            "AmountOfOutgoingFlows": 0,
            "OutgoingFlows": [],
            "AmountOfIncomingFlows": 0
        },
        {
            "ThreadID": 6,
            "ThreadName": "Source5",
            "AmountOfOutgoingFlows": 0,
            "OutgoingFlows": [],
            "AmountOfIncomingFlows": 0
        },
        {
            "ThreadID": 7,
            "ThreadName": "Source6",
            "AmountOfOutgoingFlows": 8,
            "OutgoingFlows": [
                {
                    "MSGAmount": 1,
                    "SourceThread": "Source6",
                    "FlowType": "CBR",
                    "Header": [
                        "ADDR",
                        "SIZE"
                    ],
                    "StopTime": 0,
                    "Bandwidth": 1000,
                    "Payload": [
                        "0000FFFF",
                        "00040019"
                    ],
                    "TargetThread": "Sink",
                    "Periodic": false,
                    "StartTime": 0
                },
                {
                    "MSGAmount": 1,
                    "SourceThread": "Source6",
                    "FlowType": "CBR",
                    "Header": [
                        "ADDR",
                        "SIZE"
                    ],
                    "StopTime": 0,
                    "Bandwidth": 1000,
                    "Payload": [
                        "0000FFFF",
                        "400C007D"
                    ],
                    "TargetThread": "Sink",
                    "Periodic": false,
                    "StartTime": 0
                },
                {
                    "MSGAmount": 1,
                    "SourceThread": "Source6",
                    "FlowType": "CBR",
                    "Header": [
                        "ADDR",
                        "SIZE"
                    ],
                    "StopTime": 0,
                    "Bandwidth": 1000,
                    "Payload": [
                        "0000FFFF",
                        "0145986A"
                    ],
                    "TargetThread": "Sink",
                    "Periodic": false,
                    "StartTime": 1000000
                },
                {
                    "MSGAmount": 1,
                    "SourceThread": "Source6",
                    "FlowType": "CBR",
                    "Header": [
                        "ADDR",
                        "SIZE"
                    ],
                    "StopTime": 0,
                    "Bandwidth": 1000,
                    "Payload": [
                        "0000FFFF",
                        "405A8C35"
                    ],
                    "TargetThread": "Sink",
                    "Periodic": false,
                    "StartTime": 1000000
                },
                {
                    "MSGAmount": 1,
                    "SourceThread": "Source6",
                    "FlowType": "CBR",
                    "Header": [
                        "ADDR",
                        "SIZE"
                    ],
                    "StopTime": 0,
                    "Bandwidth": 1000,
                    "Payload": [
                        "0000FFFF",
                        "004B83E8"
                    ],
                    "TargetThread": "Sink",
                    "Periodic": false,
                    "StartTime": 2000000
                },
                {
                    "MSGAmount": 1,
                    "SourceThread": "Source6",
                    "FlowType": "CBR",
                    "Header": [
                        "ADDR",
                        "SIZE"
                    ],
                    "StopTime": 0,
                    "Bandwidth": 1000,
                    "Payload": [
                        "0000FFFF",
                        "406E87D0"
                    ],
                    "TargetThread": "Sink",
                    "Periodic": false,
                    "StartTime": 2000000
                },
                {
                    "MSGAmount": 1,
                    "SourceThread": "Source6",
                    "FlowType": "CBR",
                    "Header": [
                        "ADDR",
                        "SIZE"
                    ],
                    "StopTime": 0,
                    "Bandwidth": 1000,
                    "Payload": [
                        "0000FFFF",
                        "006083E8"
                    ],
                    "TargetThread": "Sink",
                    "Periodic": false,
                    "StartTime": 3000000
                },
                {
                    "MSGAmount": 1,
                    "SourceThread": "Source6",
                    "FlowType": "CBR",
                    "Header": [
                        "ADDR",
                        "SIZE"
                    ],
                    "StopTime": 0,
                    "Bandwidth": 1000,
                    "Payload": [
                        "0000FFFF",
                        "408087D0"
                    ],
                    "TargetThread": "Sink",
                    "Periodic": false,
                    "StartTime": 3000000
                }
            ],
            "AmountOfIncomingFlows": 0
        },
        {
            "ThreadID": 8,
            "ThreadName": "Source7",
            "AmountOfOutgoingFlows": 4,
            "OutgoingFlows": [
                {
                    "MSGAmount": 1,
                    "SourceThread": "Source7",
                    "FlowType": "CBR",
                    "Header": [
                        "ADDR",
                        "SIZE"
                    ],
                    "StopTime": 0,
                    "Bandwidth": 1000,
                    "Payload": [
                        "0000FFFF",
                        "4008007D"
                    ],
                    "TargetThread": "Sink",
                    "Periodic": false,
                    "StartTime": 0
                },
                {
                    "MSGAmount": 1,
                    "SourceThread": "Source7",
                    "FlowType": "CBR",
                    "Header": [
                        "ADDR",
                        "SIZE"
                    ],
                    "StopTime": 0,
                    "Bandwidth": 1000,
                    "Payload": [
                        "0000FFFF",
                        "4000FFFF"
                    ],
                    "TargetThread": "Sink",
                    "Periodic": false,
                    "StartTime": 1000000
                },
                {
                    "MSGAmount": 1,
                    "SourceThread": "Source7",
                    "FlowType": "CBR",
                    "Header": [
                        "ADDR",
                        "SIZE"
                    ],
                    "StopTime": 0,
                    "Bandwidth": 1000,
                    "Payload": [
                        "0000FFFF",
                        "40BA83E8"
                    ],
                    "TargetThread": "Sink",
                    "Periodic": false,
                    "StartTime": 2000000
                },
                {
                    "MSGAmount": 1,
                    "SourceThread": "Source7",
                    "FlowType": "CBR",
                    "Header": [
                        "ADDR",
                        "SIZE"
                    ],
                    "StopTime": 0,
                    "Bandwidth": 1000,
                    "Payload": [
                        "0000FFFF",
                        "4008007D"
                    ],
                    "TargetThread": "Sink",
                    "Periodic": false,
                    "StartTime": 3000000
                }
            ],
            "AmountOfIncomingFlows": 0
        },
        {
            "ThreadID": 9,
            "ThreadName": "Source8",
            "AmountOfOutgoingFlows": 4,
            "OutgoingFlows": [
                {
                    "MSGAmount": 1,
                    "SourceThread": "Source8",
                    "FlowType": "CBR",
                    "Header": [
                        "ADDR",
                        "SIZE"
                    ],
                    "StopTime": 0,
                    "Bandwidth": 1000,
                    "Payload": [
                        "0000FFFF",
                        "4004007D"
                    ],
                    "TargetThread": "Sink",
                    "Periodic": false,
                    "StartTime": 0
                },
                {
                    "MSGAmount": 1,
                    "SourceThread": "Source8",
                    "FlowType": "CBR",
                    "Header": [
                        "ADDR",
                        "SIZE"
                    ],
                    "StopTime": 0,
                    "Bandwidth": 1000,
                    "Payload": [
                        "0000FFFF",
                        "4000FFFF"
                    ],
                    "TargetThread": "Sink",
                    "Periodic": false,
                    "StartTime": 1000000
                },
                {
                    "MSGAmount": 1,
                    "SourceThread": "Source8",
                    "FlowType": "CBR",
                    "Header": [
                        "ADDR",
                        "SIZE"
                    ],
                    "StopTime": 0,
                    "Bandwidth": 1000,
                    "Payload": [
                        "0000FFFF",
                        "40B083E8"
                    ],
                    "TargetThread": "Sink",
                    "Periodic": false,
                    "StartTime": 2000000
                },
                {
                    "MSGAmount": 1,
                    "SourceThread": "Source8",
                    "FlowType": "CBR",
                    "Header": [
                        "ADDR",
                        "SIZE"
                    ],
                    "StopTime": 0,
                    "Bandwidth": 1000,
                    "Payload": [
                        "0000FFFF",
                        "4004007D"
                    ],
                    "TargetThread": "Sink",
                    "Periodic": false,
                    "StartTime": 3000000
                }
            ],
            "AmountOfIncomingFlows": 0
        },
        {
            "ThreadID": 10,
            "ThreadName": "Source9",
            "AmountOfOutgoingFlows": 8,
            "OutgoingFlows": [
                {
                    "MSGAmount": 1,
                    "SourceThread": "Source9",
                    "FlowType": "CBR",
                    "Header": [
                        "ADDR",
                        "SIZE"
                    ],
                    "StopTime": 0,
                    "Bandwidth": 1000,
                    "Payload": [
                        "0000FFFF",
                        "017FB98D"
                    ],
                    "TargetThread": "Sink",
                    "Periodic": false,
                    "StartTime": 0
                },
                {
                    "MSGAmount": 1,
                    "SourceThread": "Source9",
                    "FlowType": "CBR",
                    "Header": [
                        "ADDR",
                        "SIZE"
                    ],
                    "StopTime": 0,
                    "Bandwidth": 1000,
                    "Payload": [
                        "0000FFFF",
                        "405A986A"
                    ],
                    "TargetThread": "Sink",
                    "Periodic": false,
                    "StartTime": 0
                },
                {
                    "MSGAmount": 1,
                    "SourceThread": "Source9",
                    "FlowType": "CBR",
                    "Header": [
                        "ADDR",
                        "SIZE"
                    ],
                    "StopTime": 0,
                    "Bandwidth": 1000,
                    "Payload": [
                        "0000FFFF",
                        "0145986A"
                    ],
                    "TargetThread": "Sink",
                    "Periodic": false,
                    "StartTime": 1000000
                },
                {
                    "MSGAmount": 1,
                    "SourceThread": "Source9",
                    "FlowType": "CBR",
                    "Header": [
                        "ADDR",
                        "SIZE"
                    ],
                    "StopTime": 0,
                    "Bandwidth": 1000,
                    "Payload": [
                        "0000FFFF",
                        "405A8C35"
                    ],
                    "TargetThread": "Sink",
                    "Periodic": false,
                    "StartTime": 1000000
                },
                {
                    "MSGAmount": 1,
                    "SourceThread": "Source9",
                    "FlowType": "CBR",
                    "Header": [
                        "ADDR",
                        "SIZE"
                    ],
                    "StopTime": 0,
                    "Bandwidth": 1000,
                    "Payload": [
                        "0000FFFF",
                        "003083E8"
                    ],
                    "TargetThread": "Sink",
                    "Periodic": false,
                    "StartTime": 2000000
                },
                {
                    "MSGAmount": 1,
                    "SourceThread": "Source9",
                    "FlowType": "CBR",
                    "Header": [
                        "ADDR",
                        "SIZE"
                    ],
                    "StopTime": 0,
                    "Bandwidth": 1000,
                    "Payload": [
                        "0000FFFF",
                        "400E8190"
                    ],
                    "TargetThread": "Sink",
                    "Periodic": false,
                    "StartTime": 2000000
                },
                {
                    "MSGAmount": 1,
                    "SourceThread": "Source9",
                    "FlowType": "CBR",
                    "Header": [
                        "ADDR",
                        "SIZE"
                    ],
                    "StopTime": 0,
                    "Bandwidth": 1000,
                    "Payload": [
                        "0000FFFF",
                        "0145986A"
                    ],
                    "TargetThread": "Sink",
                    "Periodic": false,
                    "StartTime": 3000000
                },
                {
                    "MSGAmount": 1,
                    "SourceThread": "Source9",
                    "FlowType": "CBR",
                    "Header": [
                        "ADDR",
                        "SIZE"
                    ],
                    "StopTime": 0,
                    "Bandwidth": 1000,
                    "Payload": [
                        "0000FFFF",
                        "405A8C35"
                    ],
                    "TargetThread": "Sink",
                    "Periodic": false,
                    "StartTime": 3000000
                }
            ],
            "AmountOfIncomingFlows": 0
        },
        {
            "ThreadID": 11,
            "ThreadName": "Source10",
            "AmountOfOutgoingFlows": 0,
            "OutgoingFlows": [],
            "AmountOfIncomingFlows": 0
        },
        {
            "ThreadID": 12,
            "ThreadName": "Source11",
            "AmountOfOutgoingFlows": 0,
            "OutgoingFlows": [],
            "AmountOfIncomingFlows": 0
        },
        {
            "ThreadID": 13,
            "ThreadName": "Source12",
            "AmountOfOutgoingFlows": 4,
            "OutgoingFlows": [
                {
                    "MSGAmount": 1,
                    "SourceThread": "Source12",
                    "FlowType": "CBR",
                    "Header": [
                        "ADDR",
                        "SIZE"
                    ],
                    "StopTime": 0,
                    "Bandwidth": 1000,
                    "Payload": [
                        "0000FFFF",
                        "4004007D"
                    ],
                    "TargetThread": "Sink",
                    "Periodic": false,
                    "StartTime": 0
                },
                {
                    "MSGAmount": 1,
                    "SourceThread": "Source12",
                    "FlowType": "CBR",
                    "Header": [
                        "ADDR",
                        "SIZE"
                    ],
                    "StopTime": 0,
                    "Bandwidth": 1000,
                    "Payload": [
                        "0000FFFF",
                        "40048064"
                    ],
                    "TargetThread": "Sink",
                    "Periodic": false,
                    "StartTime": 1000000
                },
                {
                    "MSGAmount": 1,
                    "SourceThread": "Source12",
                    "FlowType": "CBR",
                    "Header": [
                        "ADDR",
                        "SIZE"
                    ],
                    "StopTime": 0,
                    "Bandwidth": 1000,
                    "Payload": [
                        "0000FFFF",
                        "40008014"
                    ],
                    "TargetThread": "Sink",
                    "Periodic": false,
                    "StartTime": 2000000
                },
                {
                    "MSGAmount": 1,
                    "SourceThread": "Source12",
                    "FlowType": "CBR",
                    "Header": [
                        "ADDR",
                        "SIZE"
                    ],
                    "StopTime": 0,
                    "Bandwidth": 1000,
                    "Payload": [
                        "0000FFFF",
                        "40008014"
                    ],
                    "TargetThread": "Sink",
                    "Periodic": false,
                    "StartTime": 3000000
                }
            ],
            "AmountOfIncomingFlows": 0
        },
        {
            "ThreadID": 14,
            "ThreadName": "Source13",
            "AmountOfOutgoingFlows": 4,
            "OutgoingFlows": [
                {
                    "MSGAmount": 1,
                    "SourceThread": "Source13",
                    "FlowType": "CBR",
                    "Header": [
                        "ADDR",
                        "SIZE"
                    ],
                    "StopTime": 0,
                    "Bandwidth": 1000,
                    "Payload": [
                        "0000FFFF",
                        "4006007D"
                    ],
                    "TargetThread": "Sink",
                    "Periodic": false,
                    "StartTime": 0
                },
                {
                    "MSGAmount": 1,
                    "SourceThread": "Source13",
                    "FlowType": "CBR",
                    "Header": [
                        "ADDR",
                        "SIZE"
                    ],
                    "StopTime": 0,
                    "Bandwidth": 1000,
                    "Payload": [
                        "0000FFFF",
                        "401801EB"
                    ],
                    "TargetThread": "Sink",
                    "Periodic": false,
                    "StartTime": 1000000
                },
                {
                    "MSGAmount": 1,
                    "SourceThread": "Source13",
                    "FlowType": "CBR",
                    "Header": [
                        "ADDR",
                        "SIZE"
                    ],
                    "StopTime": 0,
                    "Bandwidth": 1000,
                    "Payload": [
                        "0000FFFF",
                        "40B083E8"
                    ],
                    "TargetThread": "Sink",
                    "Periodic": false,
                    "StartTime": 2000000
                },
                {
                    "MSGAmount": 1,
                    "SourceThread": "Source13",
                    "FlowType": "CBR",
                    "Header": [
                        "ADDR",
                        "SIZE"
                    ],
                    "StopTime": 0,
                    "Bandwidth": 1000,
                    "Payload": [
                        "0000FFFF",
                        "400C007D"
                    ],
                    "TargetThread": "Sink",
                    "Periodic": false,
                    "StartTime": 3000000
                }
            ],
            "AmountOfIncomingFlows": 0
        },
        {
            "ThreadID": 15,
            "ThreadName": "Source14",
            "AmountOfOutgoingFlows": 4,
            "OutgoingFlows": [
                {
                    "MSGAmount": 1,
                    "SourceThread": "Source14",
                    "FlowType": "CBR",
                    "Header": [
                        "ADDR",
                        "SIZE"
                    ],
                    "StopTime": 0,
                    "Bandwidth": 1000,
                    "Payload": [
                        "0000FFFF",
                        "431A7EF5"
                    ],
                    "TargetThread": "Sink",
                    "Periodic": false,
                    "StartTime": 0
                },
                {
                    "MSGAmount": 1,
                    "SourceThread": "Source14",
                    "FlowType": "CBR",
                    "Header": [
                        "ADDR",
                        "SIZE"
                    ],
                    "StopTime": 0,
                    "Bandwidth": 1000,
                    "Payload": [
                        "0000FFFF",
                        "401801EB"
                    ],
                    "TargetThread": "Sink",
                    "Periodic": false,
                    "StartTime": 1000000
                },
                {
                    "MSGAmount": 1,
                    "SourceThread": "Source14",
                    "FlowType": "CBR",
                    "Header": [
                        "ADDR",
                        "SIZE"
                    ],
                    "StopTime": 0,
                    "Bandwidth": 1000,
                    "Payload": [
                        "0000FFFF",
                        "C0020005"
                    ],
                    "TargetThread": "Sink",
                    "Periodic": false,
                    "StartTime": 2000000
                },
                {
                    "MSGAmount": 1,
                    "SourceThread": "Source14",
                    "FlowType": "CBR",
                    "Header": [
                        "ADDR",
                        "SIZE"
                    ],
                    "StopTime": 0,
                    "Bandwidth": 1000,
                    "Payload": [
                        "0000FFFF",
                        "401801EB"
                    ],
                    "TargetThread": "Sink",
                    "Periodic": false,
                    "StartTime": 3000000
                }
            ],
            "AmountOfIncomingFlows": 0
        },
        {
            "ThreadID": 16,
            "ThreadName": "Source15",
            "AmountOfOutgoingFlows": 4,
            "OutgoingFlows": [
                {
                    "MSGAmount": 1,
                    "SourceThread": "Source15",
                    "FlowType": "CBR",
                    "Header": [
                        "ADDR",
                        "SIZE"
                    ],
                    "StopTime": 0,
                    "Bandwidth": 1000,
                    "Payload": [
                        "0000FFFF",
                        "404A0C35"
                    ],
                    "TargetThread": "Sink",
                    "Periodic": false,
                    "StartTime": 0
                },
                {
                    "MSGAmount": 1,
                    "SourceThread": "Source15",
                    "FlowType": "CBR",
                    "Header": [
                        "ADDR",
                        "SIZE"
                    ],
                    "StopTime": 0,
                    "Bandwidth": 1000,
                    "Payload": [
                        "0000FFFF",
                        "40048064"
                    ],
                    "TargetThread": "Sink",
                    "Periodic": false,
                    "StartTime": 1000000
                },
                {
                    "MSGAmount": 1,
                    "SourceThread": "Source15",
                    "FlowType": "CBR",
                    "Header": [
                        "ADDR",
                        "SIZE"
                    ],
                    "StopTime": 0,
                    "Bandwidth": 1000,
                    "Payload": [
                        "0000FFFF",
                        "40008014"
                    ],
                    "TargetThread": "Sink",
                    "Periodic": false,
                    "StartTime": 2000000
                },
                {
                    "MSGAmount": 1,
                    "SourceThread": "Source15",
                    "FlowType": "CBR",
                    "Header": [
                        "ADDR",
                        "SIZE"
                    ],
                    "StopTime": 0,
                    "Bandwidth": 1000,
                    "Payload": [
                        "0000FFFF",
                        "418FA0EF"
                    ],
                    "TargetThread": "Sink",
                    "Periodic": false,
                    "StartTime": 3000000
                }
            ],
            "AmountOfIncomingFlows": 0
        },
        {
            "ThreadID": 17,
            "ThreadName": "Source16",
            "AmountOfOutgoingFlows": 0,
            "OutgoingFlows": [],
            "AmountOfIncomingFlows": 0
        },
        {
            "ThreadID": 18,
            "ThreadName": "Source17",
            "AmountOfOutgoingFlows": 0,
            "OutgoingFlows": [],
            "AmountOfIncomingFlows": 0
        },
        {
            "ThreadID": 19,
            "ThreadName": "Source18",
            "AmountOfOutgoingFlows": 8,
            "OutgoingFlows": [
                {
                    "MSGAmount": 1,
                    "SourceThread": "Source18",
                    "FlowType": "CBR",
                    "Header": [
                        "ADDR",
                        "SIZE"
                    ],
                    "StopTime": 0,
                    "Bandwidth": 1000,
                    "Payload": [
                        "0000FFFF",
                        "000C007D"
                    ],
                    "TargetThread": "Sink",
                    "Periodic": false,
                    "StartTime": 0
                },
                {
                    "MSGAmount": 1,
                    "SourceThread": "Source18",
                    "FlowType": "CBR",
                    "Header": [
                        "ADDR",
                        "SIZE"
                    ],
                    "StopTime": 0,
                    "Bandwidth": 1000,
                    "Payload": [
                        "0000FFFF",
                        "40020019"
                    ],
                    "TargetThread": "Sink",
                    "Periodic": false,
                    "StartTime": 0
                },
                {
                    "MSGAmount": 1,
                    "SourceThread": "Source18",
                    "FlowType": "CBR",
                    "Header": [
                        "ADDR",
                        "SIZE"
                    ],
                    "StopTime": 0,
                    "Bandwidth": 1000,
                    "Payload": [
                        "0000FFFF",
                        "80018005"
                    ],
                    "TargetThread": "Sink",
                    "Periodic": false,
                    "StartTime": 1000000
                },
                {
                    "MSGAmount": 1,
                    "SourceThread": "Source18",
                    "FlowType": "CBR",
                    "Header": [
                        "ADDR",
                        "SIZE"
                    ],
                    "StopTime": 0,
                    "Bandwidth": 1000,
                    "Payload": [
                        "0000FFFF",
                        "42429869"
                    ],
                    "TargetThread": "Sink",
                    "Periodic": false,
                    "StartTime": 1000000
                },
                {
                    "MSGAmount": 1,
                    "SourceThread": "Source18",
                    "FlowType": "CBR",
                    "Header": [
                        "ADDR",
                        "SIZE"
                    ],
                    "StopTime": 0,
                    "Bandwidth": 1000,
                    "Payload": [
                        "0000FFFF",
                        "839987D0"
                    ],
                    "TargetThread": "Sink",
                    "Periodic": false,
                    "StartTime": 2000000
                },
                {
                    "MSGAmount": 1,
                    "SourceThread": "Source18",
                    "FlowType": "CBR",
                    "Header": [
                        "ADDR",
                        "SIZE"
                    ],
                    "StopTime": 0,
                    "Bandwidth": 1000,
                    "Payload": [
                        "0000FFFF",
                        "40008014"
                    ],
                    "TargetThread": "Sink",
                    "Periodic": false,
                    "StartTime": 2000000
                },
                {
                    "MSGAmount": 1,
                    "SourceThread": "Source18",
                    "FlowType": "CBR",
                    "Header": [
                        "ADDR",
                        "SIZE"
                    ],
                    "StopTime": 0,
                    "Bandwidth": 1000,
                    "Payload": [
                        "0000FFFF",
                        "839987D0"
                    ],
                    "TargetThread": "Sink",
                    "Periodic": false,
                    "StartTime": 3000000
                },
                {
                    "MSGAmount": 1,
                    "SourceThread": "Source18",
                    "FlowType": "CBR",
                    "Header": [
                        "ADDR",
                        "SIZE"
                    ],
                    "StopTime": 0,
                    "Bandwidth": 1000,
                    "Payload": [
                        "0000FFFF",
                        "40008014"
                    ],
                    "TargetThread": "Sink",
                    "Periodic": false,
                    "StartTime": 3000000
                }
            ],
            "AmountOfIncomingFlows": 0
        },
        {
            "ThreadID": 20,
            "ThreadName": "Source19",
            "AmountOfOutgoingFlows": 4,
            "OutgoingFlows": [
                {
                    "MSGAmount": 1,
                    "SourceThread": "Source19",
                    "FlowType": "CBR",
                    "Header": [
                        "ADDR",
                        "SIZE"
                    ],
                    "StopTime": 0,
                    "Bandwidth": 1000,
                    "Payload": [
                        "0000FFFF",
                        "4006007D"
                    ],
                    "TargetThread": "Sink",
                    "Periodic": false,
                    "StartTime": 0
                },
                {
                    "MSGAmount": 1,
                    "SourceThread": "Source19",
                    "FlowType": "CBR",
                    "Header": [
                        "ADDR",
                        "SIZE"
                    ],
                    "StopTime": 0,
                    "Bandwidth": 1000,
                    "Payload": [
                        "0000FFFF",
                        "401801EB"
                    ],
                    "TargetThread": "Sink",
                    "Periodic": false,
                    "StartTime": 1000000
                },
                {
                    "MSGAmount": 1,
                    "SourceThread": "Source19",
                    "FlowType": "CBR",
                    "Header": [
                        "ADDR",
                        "SIZE"
                    ],
                    "StopTime": 0,
                    "Bandwidth": 1000,
                    "Payload": [
                        "0000FFFF",
                        "40D383E8"
                    ],
                    "TargetThread": "Sink",
                    "Periodic": false,
                    "StartTime": 2000000
                },
                {
                    "MSGAmount": 1,
                    "SourceThread": "Source19",
                    "FlowType": "CBR",
                    "Header": [
                        "ADDR",
                        "SIZE"
                    ],
                    "StopTime": 0,
                    "Bandwidth": 1000,
                    "Payload": [
                        "0000FFFF",
                        "40008019"
                    ],
                    "TargetThread": "Sink",
                    "Periodic": false,
                    "StartTime": 3000000
                }
            ],
            "AmountOfIncomingFlows": 0
        },
        {
            "ThreadID": 21,
            "ThreadName": "Source20",
            "AmountOfOutgoingFlows": 4,
            "OutgoingFlows": [
                {
                    "MSGAmount": 1,
                    "SourceThread": "Source20",
                    "FlowType": "CBR",
                    "Header": [
                        "ADDR",
                        "SIZE"
                    ],
                    "StopTime": 0,
                    "Bandwidth": 1000,
                    "Payload": [
                        "0000FFFF",
                        "431A7EF5"
                    ],
                    "TargetThread": "Sink",
                    "Periodic": false,
                    "StartTime": 0
                },
                {
                    "MSGAmount": 1,
                    "SourceThread": "Source20",
                    "FlowType": "CBR",
                    "Header": [
                        "ADDR",
                        "SIZE"
                    ],
                    "StopTime": 0,
                    "Bandwidth": 1000,
                    "Payload": [
                        "0000FFFF",
                        "401801EB"
                    ],
                    "TargetThread": "Sink",
                    "Periodic": false,
                    "StartTime": 1000000
                },
                {
                    "MSGAmount": 1,
                    "SourceThread": "Source20",
                    "FlowType": "CBR",
                    "Header": [
                        "ADDR",
                        "SIZE"
                    ],
                    "StopTime": 0,
                    "Bandwidth": 1000,
                    "Payload": [
                        "0000FFFF",
                        "C09481F4"
                    ],
                    "TargetThread": "Sink",
                    "Periodic": false,
                    "StartTime": 2000000
                },
                {
                    "MSGAmount": 1,
                    "SourceThread": "Source20",
                    "FlowType": "CBR",
                    "Header": [
                        "ADDR",
                        "SIZE"
                    ],
                    "StopTime": 0,
                    "Bandwidth": 1000,
                    "Payload": [
                        "0000FFFF",
                        "401801EB"
                    ],
                    "TargetThread": "Sink",
                    "Periodic": false,
                    "StartTime": 3000000
                }
            ],
            "AmountOfIncomingFlows": 0
        },
        {
            "ThreadID": 22,
            "ThreadName": "Source21",
            "AmountOfOutgoingFlows": 8,
            "OutgoingFlows": [
                {
                    "MSGAmount": 1,
                    "SourceThread": "Source21",
                    "FlowType": "CBR",
                    "Header": [
                        "ADDR",
                        "SIZE"
                    ],
                    "StopTime": 0,
                    "Bandwidth": 1000,
                    "Payload": [
                        "0000FFFF",
                        "0001800A"
                    ],
                    "TargetThread": "Sink",
                    "Periodic": false,
                    "StartTime": 0
                },
                {
                    "MSGAmount": 1,
                    "SourceThread": "Source21",
                    "FlowType": "CBR",
                    "Header": [
                        "ADDR",
                        "SIZE"
                    ],
                    "StopTime": 0,
                    "Bandwidth": 1000,
                    "Payload": [
                        "0000FFFF",
                        "402E83E8"
                    ],
                    "TargetThread": "Sink",
                    "Periodic": false,
                    "StartTime": 0
                },
                {
                    "MSGAmount": 1,
                    "SourceThread": "Source21",
                    "FlowType": "CBR",
                    "Header": [
                        "ADDR",
                        "SIZE"
                    ],
                    "StopTime": 0,
                    "Bandwidth": 1000,
                    "Payload": [
                        "0000FFFF",
                        "80018005"
                    ],
                    "TargetThread": "Sink",
                    "Periodic": false,
                    "StartTime": 1000000
                },
                {
                    "MSGAmount": 1,
                    "SourceThread": "Source21",
                    "FlowType": "CBR",
                    "Header": [
                        "ADDR",
                        "SIZE"
                    ],
                    "StopTime": 0,
                    "Bandwidth": 1000,
                    "Payload": [
                        "0000FFFF",
                        "4B627B0B"
                    ],
                    "TargetThread": "Sink",
                    "Periodic": false,
                    "StartTime": 1000000
                },
                {
                    "MSGAmount": 1,
                    "SourceThread": "Source21",
                    "FlowType": "CBR",
                    "Header": [
                        "ADDR",
                        "SIZE"
                    ],
                    "StopTime": 0,
                    "Bandwidth": 1000,
                    "Payload": [
                        "0000FFFF",
                        "839987D0"
                    ],
                    "TargetThread": "Sink",
                    "Periodic": false,
                    "StartTime": 2000000
                },
                {
                    "MSGAmount": 1,
                    "SourceThread": "Source21",
                    "FlowType": "CBR",
                    "Header": [
                        "ADDR",
                        "SIZE"
                    ],
                    "StopTime": 0,
                    "Bandwidth": 1000,
                    "Payload": [
                        "0000FFFF",
                        "40008014"
                    ],
                    "TargetThread": "Sink",
                    "Periodic": false,
                    "StartTime": 2000000
                },
                {
                    "MSGAmount": 1,
                    "SourceThread": "Source21",
                    "FlowType": "CBR",
                    "Header": [
                        "ADDR",
                        "SIZE"
                    ],
                    "StopTime": 0,
                    "Bandwidth": 1000,
                    "Payload": [
                        "0000FFFF",
                        "80018005"
                    ],
                    "TargetThread": "Sink",
                    "Periodic": false,
                    "StartTime": 3000000
                },
                {
                    "MSGAmount": 1,
                    "SourceThread": "Source21",
                    "FlowType": "CBR",
                    "Header": [
                        "ADDR",
                        "SIZE"
                    ],
                    "StopTime": 0,
                    "Bandwidth": 1000,
                    "Payload": [
                        "0000FFFF",
                        "42979BDD"
                    ],
                    "TargetThread": "Sink",
                    "Periodic": false,
                    "StartTime": 3000000
                }
            ],
            "AmountOfIncomingFlows": 0
        },
        {
            "ThreadID": 23,
            "ThreadName": "Source22",
            "AmountOfOutgoingFlows": 0,
            "OutgoingFlows": [],
            "AmountOfIncomingFlows": 0
        },
        {
            "ThreadID": 24,
            "ThreadName": "Source23",
            "AmountOfOutgoingFlows": 0,
            "OutgoingFlows": [],
            "AmountOfIncomingFlows": 0
        },
        {
            "ThreadID": 25,
            "ThreadName": "Source24",
            "AmountOfOutgoingFlows": 0,
            "OutgoingFlows": [],
            "AmountOfIncomingFlows": 0
        },
        {
            "ThreadID": 26,
            "ThreadName": "Source25",
            "AmountOfOutgoingFlows": 0,
            "OutgoingFlows": [],
            "AmountOfIncomingFlows": 0
        },
        {
            "ThreadID": 27,
            "ThreadName": "Source26",
            "AmountOfOutgoingFlows": 0,
            "OutgoingFlows": [],
            "AmountOfIncomingFlows": 0
        },
        {
            "ThreadID": 28,
            "ThreadName": "Source27",
            "AmountOfOutgoingFlows": 0,
            "OutgoingFlows": [],
            "AmountOfIncomingFlows": 0
        },
        {
            "ThreadID": 29,
            "ThreadName": "Source28",
            "AmountOfOutgoingFlows": 0,
            "OutgoingFlows": [],
            "AmountOfIncomingFlows": 0
        },
        {
            "ThreadID": 30,
            "ThreadName": "Source29",
            "AmountOfOutgoingFlows": 0,
            "OutgoingFlows": [],
            "AmountOfIncomingFlows": 0
        },
        {
            "ThreadID": 31,
            "ThreadName": "Source30",
            "AmountOfOutgoingFlows": 0,
            "OutgoingFlows": [],
            "AmountOfIncomingFlows": 0
        },
        {
            "ThreadID": 32,
            "ThreadName": "Source31",
            "AmountOfOutgoingFlows": 0,
            "OutgoingFlows": [],
            "AmountOfIncomingFlows": 0
        },
        {
            "ThreadID": 33,
            "ThreadName": "Source32",
            "AmountOfOutgoingFlows": 0,
            "OutgoingFlows": [],
            "AmountOfIncomingFlows": 0
        },
        {
            "ThreadID": 34,
            "ThreadName": "Source33",
            "AmountOfOutgoingFlows": 0,
            "OutgoingFlows": [],
            "AmountOfIncomingFlows": 0
        },
        {
            "ThreadID": 35,
            "ThreadName": "Source34",
            "AmountOfOutgoingFlows": 0,
            "OutgoingFlows": [],
            "AmountOfIncomingFlows": 0
        },
        {
            "ThreadID": 36,
            "ThreadName": "Source35",
            "AmountOfOutgoingFlows": 0,
            "OutgoingFlows": [],
            "AmountOfIncomingFlows": 0
        }
    ],
    "StartTime": 0
}